keepalive_pkg/__init__.py
keepalive_pkg/__main__.py
https_keep_alive-0.0.1.dist-info/LICENSE
https_keep_alive-0.0.1.dist-info/METADATA
https_keep_alive-0.0.1.dist-info/WHEEL
https_keep_alive-0.0.1.dist-info/top_level.txt
https_keep_alive-0.0.1.dist-info/RECORD
